start.py
lillie_start-0.1.2.dist-info/METADATA
lillie_start-0.1.2.dist-info/WHEEL
lillie_start-0.1.2.dist-info/entry_points.txt
lillie_start-0.1.2.dist-info/top_level.txt
lillie_start-0.1.2.dist-info/RECORD
